phyper/__init__.py
phyper/chemometrics/__init__.py
phyper/chemometrics/_gui.py
phyper/chemometrics/analysis.py
phyper/chemometrics/dataset.py
phyper/chemometrics/preprocessing.py
phyper/chemometrics/sampling.py
phyper/lab/__init__.py
phyper/lab/_misc.py
phyper/lab/measurement.py
phyper-1.1.7.dist-info/LICENSE
phyper-1.1.7.dist-info/METADATA
phyper-1.1.7.dist-info/WHEEL
phyper-1.1.7.dist-info/top_level.txt
phyper-1.1.7.dist-info/RECORD
