Metadata-Version: 2.1
Name: phyper
Version: 1.1.7
Summary: Package for managing (hyper)spectral datasets
Home-page: https://gitlab.kuleuven.be/u0123403/pyper
Author: Remi Van Belleghem
Author-email: remi.vanbelleghem@kuleuven.be
Maintainer: MeBios - KULeuven
Maintainer-email: wouter.saeys@kuleuven.be
License: UNKNOWN
Keywords: hyperspectral,chemometrics
Platform: UNKNOWN
Classifier: Development Status :: 4 - Beta
Classifier: License :: OSI Approved :: MIT License
Classifier: Programming Language :: Python :: 3.7
Classifier: Programming Language :: Python :: 3.8
Classifier: Programming Language :: Python :: 3.9
Requires-Python: >=3.6,<4.0
License-File: LICENSE
Requires-Dist: matplotlib
Requires-Dist: scikit-learn
Requires-Dist: numpy
Requires-Dist: scikit-image
Requires-Dist: scipy
Requires-Dist: tqdm
Requires-Dist: h5py
Requires-Dist: pypng
Requires-Dist: datetime
Requires-Dist: opencv-python (<5,>=4)
Requires-Dist: spectral
